{
  "slug": "코드로_DB를_다루는_방법에_대하여_JDBC_SQL_Mapper_ORM_그리고_Statement_Prepar_223233787919",
  "title": "코드로 DB를 다루는 방법에 대하여 (JDBC, SQL Mapper, ORM 그리고 Statement, Preparedstatement, cursor)",
  "log_no": "223233787919",
  "date": "2026-03-30",
  "tags": [],
  "category": "Java/JPA",
  "summary": "우리가 알고 있는 디비, DB, DBMS(DataBase Management System). 이러한 DB 서버에는 어떤 것들이 있나? ​ ​ 익숙한 MySQL, Oracle 등.. ​ 이러한 데이터베이스의 종류에는 ",
  "thumb": "images/image_1.jpg",
  "source_url": "https://blog.naver.com/ghdalswl77/223233787919"
}